MANIFEST.in
readme.md
requirements.txt
setup.cfg
setup.py
VSphereClient/VSphere.py
VSphereClient/__init__.py
VSphereClient.egg-info/PKG-INFO
VSphereClient.egg-info/SOURCES.txt
VSphereClient.egg-info/dependency_links.txt
VSphereClient.egg-info/requires.txt
VSphereClient.egg-info/top_level.txt